---
title: "synchronized锁升级"
date: "2026-05-15"
updated: "2026-05-15T01:35:00.866Z"
category: "juc"
tags: ["Java", "JUC", "并发"]
---

# synchronized锁升级

## 锁升级过程
<font style="background-color:#FBF5CB;">无锁	->	偏向锁	->	轻量级锁	->	重量级锁</font>

<font style="color:#74B602;">偏向锁</font>: MarkWord存储的是偏向的线程ID;

<font style="color:#74B602;">轻量锁</font>: MarkWord存储的是指向线程栈中Lock Record的指针;

<font style="color:#74B602;">重量锁</font>:MarkWord存储的是指向堆中的monitor对象的指针;

## Monitor与java对象是如何关联的？
每一个实例对象都有一个Monitor,可以和对象一起创建和销毁。Monitor由ObjectMonitor实现（ObjectMonitor.cpp文件实现）

1.若一个java对象被某个线程锁住，则该java对象的Mark Word字段中LockWord指向monitor的起始地址

2.Monitor的Owner（ObjectMonitor.cpp中定义字段之一）字段会存放拥有相关联对象锁的线程id

## 反编译查看monitor
从反编译可以看出monitorenter与monitorexit是<font style="color:#74B602;">一对二</font>的关系，后面的monitorexit是防止代码块中出现异常导致锁无法释放的处理。

```java
public class SynTest01 {
    Object obj = new Object();
    public void fun1() {
        synchronized (obj) {System.out.println("hello");}
    }
    public static void main(String[] args) {}
}
```

```java
Compiled from "SynTest01.java"
public class SynTest01 {
  java.lang.Object obj;
	...

  public void fun1();
    Code:
       0: aload_0
       1: getfield      #3                  // Field obj:Ljava/lang/Object;
       4: dup
       5: astore_1
       6: monitorenter	//锁
       7: getstatic     #4                  // Field java/lang/System.out:Ljava/io/PrintStream;
      10: ldc           #5                  // String hello	输出语句
      12: invokevirtual #6                  // Method java/io/PrintStream.println:(Ljava/lang/String;)V
      15: aload_1
      16: monitorexit	//释放锁
      17: goto          25
      20: astore_2
      21: aload_1
      22: monitorexit	//释放锁 对异常的处理防止锁无法释放
      23: aload_2
      24: athrow	//抛出异常
      25: return
    Exception table:
       from    to  target type
           7    17    20   any
          20    23    20   any

  public static void main(java.lang.String[]);
    Code:
       0: return
}
```

### 反编译synchronized普通同步方法
调用指令将会检查方法的<font style="color:#1DC0C9;">ACC_SYNCHRONIZED访问标志</font>是否被设置如果设置了，执行线程会将先持有monitor锁，然后再执行方法，最后在方法完成(无论是正常完成还是非正常完成)时释放 monitor

```java
public class SynTest01 {
    public synchronized void  fun1() {
        System.out.println("hello");
    }
    public static void main(String[] args) {}
}
```

```java
 public synchronized void fun1();
    descriptor: ()V
    flags: (0x0021) ACC_PUBLIC, ACC_SYNCHRONIZED	//ACC_S...标志
    Code:
      stack=2, locals=1, args_size=1
         0: getstatic     #2                  // Field java/lang/System.out:Ljava/io/PrintStream;
         3: ldc           #3                  // String hello
         5: invokevirtual #4                  // Method java/io/PrintStream.println:(Ljava/lang/String;)V
         8: return
      LineNumberTable:
        line 4: 0
        line 5: 8
      LocalVariableTable:
        Start  Length  Slot  Name   Signature
            0       9     0  this   LSynTest01;
```

### 反编译synchronized静态普通同步方法
比普通方法多了一个<font style="color:#74B602;">ACC_STATIC</font>标志，从对象锁变为<font style="color:#74B602;">类锁</font>。

## 偏向锁
在实际应用运行过程中发现，“锁总是同一个线程持有，很少发生竞争”，也就是说<font style="color:#117CEE;">锁总是被第一个占用他的线程拥有，这个线程就是锁的偏向线程</font>。

那么只需要在锁第一次被拥有的时候，记录下偏向线程ID。这样偏向线程就一直持有着锁(后续这个线程进入和退出这段加了同步锁的代码块时，<font style="color:#117CEE;">不需要再次加锁和释放锁</font>。而是直接会去检查锁的MarkWord里面是不是放的自己的线程ID)。如果相等，表示偏向锁是偏向于当前线程的，就不需要再尝试获得锁了，直到竞争发生才释放锁。以后每次同步，检查锁的偏向线程ID与当前线程ID是否一致，如果一致直接进入同步。无需每次加锁解锁都去CAS更新对象头。<font style="color:#117CEE;">如果自始至终使用锁的线程只有一个</font>，很明显偏向锁几乎没有额外开销，性能极高。

如果不等，表示发生了竞争，锁已经不是总是偏向于同一个线程了，这个时候会尝试使用CAS来替换MarkWord里面的线程ID为新线程的ID，

<font style="color:#F1A2AB;">竞争成功</font>，表示之前的线程不存在了， MarkWord里面的线程ID为新线程的ID，锁不会升级，仍然为偏向锁:<font style="color:#F1A2AB;">竞争失败</font>，这时候可能需要升级变为轻量级锁，才能保证线程间公平竞争锁。注意，偏向锁只有遇到其他线程尝试竞争偏向锁时，持有偏向锁的线程才会释放锁，线程是不会主动释放偏向锁的。

###### <font style="color:#2F4BDA;">偏向锁的撤销</font>
偏向锁使用一种等到竞争出现才释放锁的机制，只有当其他线程竞争锁时，持有偏向锁的原来线程才会被撤销.撤销需要等待全局安全点(该时间点上没有字节码正在执行)，同时检查持有偏向锁的线程是否还在执行:

1.第一个线程正在执行synchronized方法(处于同步块)，它还没有执行完，其它线程来抢夺，该偏向锁会被取消掉并出现锁升级。

此时轻量级锁由原持有偏向锁的线程持有，继续执行其同步代码，而正在竞争的线程会进入自旋等待获得该轻量级锁。

2.第一个线程执行完成synchronized方法(退出同步块)，则将对象头设置成无锁状态并撤销偏向锁，重新偏向。

## 轻量级锁
### 轻量级锁加锁
加锁对应的字节码是 monitorenter 指令，JVM 执行这个指令时，首先会向当前线程栈内插入一条锁记录，锁记录内的锁引用字段保存锁对象的地址，然后将对象头中的 ，mark word 复制到锁记录的 displaced 字段中，官方称 Displaced Mark Word。然后线程尝试使用 CAS 将对象头中的 mark word 替换位指向锁记录的指针，并将其修改为当前线程持有轻量级锁的状态。如果成功，当前线程获得锁，如果失败，表示其他线程竞争锁，当前线程便尝试自旋获得锁

### 轻量级锁释放
释放锁的字节码是 moniterexit ，JVM处理这条指令时，首先从当前从当前线程栈内找到 "最后一条"锁引用字段指向当前锁对象的锁记录，将这条锁记录的锁字段设置为 null，（这一个操作不需要 CAS ，因为线程栈的数据不存在多线程访问的场景），这一步结束后，再检查这条锁记录的 displaced 字段是否有值，如果无值，说明这条锁记录是锁重入时存放的，此时只需将这条锁记录释放，即将锁记录中的锁引用字段设置为 null，这样就完成了一次锁的退出



如果不为空，说明这一次是最后一次释放该锁，displaced中存放的是 displacedMarkWord，该值对应的是无锁状态，当前线程需要把锁记录内的displaced的值 通过 CAS 的方式，设置到当前锁对象的 markword 中，这一步设置成功之后就相当于完全释放锁了，如果失败，当前锁可能已被升级为重量级锁，或者 现在已经处于膨胀状态中，需要走重量级锁的退出逻辑

## 锁与hashCode
在<font style="color:#2F4BDA;">无锁</font>状态下，Mark Word中可以存储对象的identity hash code值。当对象的hashCode0方法第一次被调用时，JVM会生成对应的identity hash code值并将该值存储到Mark Word中。

对于<font style="color:#2F4BDA;">偏向锁</font>，在线程获取偏向锁时，会用Thread D和epoch值覆盖identity hash code所在的位置。如果<font style="color:#74B602;">一个对象的hashCode0方法已经被调用过一次之后，这个对象不能被设置偏向锁</font>。因为如果可以的化，那Mark Word中的identity hash code必然会被偏向线程ld给覆盖，这就会造成同一个对象前后两次调用hashCode()方法得到的结果不一致。<font style="color:#74B602;">偏向锁对象调用hashCode是会膨胀为重量锁，若先计算过hashCode再加锁则直接变为轻量级锁。</font>

升级为<font style="color:#2F4BDA;">轻量级锁</font>时，JVM会在当前线程的栈帧中创建一个锁记录(Lock Record)空间，用于存储锁对象的Mak Word拷贝，该拷贝中可以包含identity hash code，所以轻量级锁可以和identity hash code共存，哈希码和GC年龄自然保存在此，释放锁后会将这些信息写回到对象头。

升级为<font style="color:#2F4BDA;">重量级锁</font>后，Mark Word保存的重量级锁指针，代表重量级锁的ObjectMonitor类里有字段记录非加锁状态下的Mark Word，锁释放后也会将信息写回到对象头。

## 锁消除
这样写 会造成锁失效 称作<font style="color:#81DFE4;">锁消除</font>

```java
public class test01 {
    //锁消除
    public static void main(String[] args) {
        test01 test01 = new test01();
        for (int i=0; i < 10; i++) {
            new Thread(test01::testFun).start();
        }
    }
    public void testFun() {
        Object obj = new Object();	//每次拿到的锁都是新的
        synchronized (obj) {
            System.out.println(obj.hashCode());
        }
    }
}
```

## 锁粗化
JIT编译时会自动优化成一个 称作 <font style="color:#81DFE4;">锁粗化</font>

```java
public class test01 {
    //锁粗化
    public static void main(String[] args) {
        Object obj = new Object();
        new Thread(() -> {
            synchronized (obj) {
                System.out.println("1");
            }
            synchronized (obj) {
                System.out.println("2");
            }
            synchronized (obj) {
                System.out.println("3");
            }
        }).start();
    }
}

```

```java
public class test01 {
    //锁粗化
    public static void main(String[] args) {
        Object obj = new Object();
        new Thread(() -> {
            synchronized (obj) {
                System.out.println("1");
                System.out.println("2");
                System.out.println("3");
            }
        }).start();
    }
}
```



> 更新: 2023-01-25 17:52:39  
> 原文: <https://www.yuque.com/kugua-4bekq/fo2wrz/aqs6z391iq1386bl>